banko_ai/__init__.py
banko_ai/__main__.py
banko_ai/cli.py
banko_ai/ai_providers/__init__.py
banko_ai/ai_providers/aws_provider.py
banko_ai/ai_providers/base.py
banko_ai/ai_providers/factory.py
banko_ai/ai_providers/gemini_provider.py
banko_ai/ai_providers/openai_provider.py
banko_ai/ai_providers/watsonx_provider.py
banko_ai/config/__init__.py
banko_ai/config/settings.py
banko_ai/static/Anallytics.png
banko_ai/static/Graph.png
banko_ai/static/Graph2.png
banko_ai/static/ai-status.png
banko_ai/static/aws-bedrock-icon.svg
banko_ai/static/banko-ai-assistant-watsonx.gif
banko_ai/static/banko-db-ops.png
banko_ai/static/banko-response.png
banko_ai/static/cache-stats.png
banko_ai/static/creditcard.png
banko_ai/static/google-gemini-icon.svg
banko_ai/static/openai-icon.svg
banko_ai/static/profilepic.jpeg
banko_ai/static/query_watcher.png
banko_ai/static/roach-logo.svg
banko_ai/static/watsonx-icon.svg
banko_ai/static/creditcard_files/0dbda187ceb472a466dff54b7015b1d4.jpg
banko_ai/static/creditcard_files/10903-7f8736e237ced107.mjs
banko_ai/static/creditcard_files/10966-809952783184ae4b.mjs
banko_ai/static/creditcard_files/13351-8a7dda060266efff.mjs
banko_ai/static/creditcard_files/1342-c79d3d17da82f23c.mjs
banko_ai/static/creditcard_files/16142-bdecf7bfdd6d70ae.mjs
banko_ai/static/creditcard_files/16550-e89f65017860221d.mjs
banko_ai/static/creditcard_files/17492-942c70b114fdcce1.mjs
banko_ai/static/creditcard_files/18352-481d67e871cc6985.mjs
banko_ai/static/creditcard_files/18555-0d9763eb744f7a77.mjs
banko_ai/static/creditcard_files/19437-575ba467ea85e866.mjs
banko_ai/static/creditcard_files/1aca1669c3b4a07f0966c4733c939d6d.jpg
banko_ai/static/creditcard_files/20126-602c15db592cf3c4.mjs
banko_ai/static/creditcard_files/20224-b6de2c08cc8ad497.mjs
banko_ai/static/creditcard_files/2029a63f9af76541f860b6a6a4ec0c90.jpg
banko_ai/static/creditcard_files/21662-1214728138c72aa2.css
banko_ai/static/creditcard_files/22517-5f7ab2631d424b77.mjs
banko_ai_assistant-1.0.34.dist-info/licenses/LICENSE
banko_ai_assistant-1.0.34.dist-info/METADATA
banko_ai_assistant-1.0.34.dist-info/WHEEL
banko_ai_assistant-1.0.34.dist-info/entry_points.txt
banko_ai_assistant-1.0.34.dist-info/top_level.txt
banko_ai_assistant-1.0.34.dist-info/RECORD
