Metadata-Version: 2.4
Name: banko-ai-assistant
Version: 1.0.34
Summary: AI-powered expense analysis and RAG system with CockroachDB vector search and multi-provider AI support (OpenAI, AWS Bedrock, IBM Watsonx, Google Gemini)
Author-email: Virag Tripathi <virag.tripathi@gmail.com>
License-Expression: MIT
Project-URL: Homepage, https://github.com/cockroachlabs-field/banko-ai-assistant-rag-demo
Project-URL: Repository, https://github.com/cockroachlabs-field/banko-ai-assistant-rag-demo
Project-URL: Documentation, https://github.com/cockroachlabs-field/banko-ai-assistant-rag-demo#readme
Project-URL: Bug Tracker, https://github.com/cockroachlabs-field/banko-ai-assistant-rag-demo/issues
Keywords: ai,rag,vector-search,cockroachdb,expense-analysis,financial-ai
Classifier: Development Status :: 5 - Production/Stable
Classifier: Intended Audience :: Developers
Classifier: Intended Audience :: Financial and Insurance Industry
Classifier: Topic :: Office/Business :: Financial
Classifier: Topic :: Scientific/Engineering :: Artificial Intelligence
Classifier: Programming Language :: Python :: 3
Classifier: Programming Language :: Python :: 3.8
Classifier: Programming Language :: Python :: 3.9
Classifier: Programming Language :: Python :: 3.10
Classifier: Programming Language :: Python :: 3.11
Classifier: Programming Language :: Python :: 3.12
Classifier: Operating System :: OS Independent
Requires-Python: >=3.8
License-File: LICENSE
Requires-Dist: flask<4.0.0,>=3.0.0
Requires-Dist: werkzeug<4.0.0,>=3.0.0
Requires-Dist: jinja2<4.0.0,>=3.1.0
Requires-Dist: psycopg2-binary<3.0.0,>=2.9.0
Requires-Dist: sqlalchemy<3.0.0,>=2.0.0
Requires-Dist: sqlalchemy-cockroachdb<3.0.0,>=2.0.0
Requires-Dist: sentence-transformers<4.0.0,>=3.1.0
Requires-Dist: boto3<1.41.0,>=1.40.0
Requires-Dist: botocore<1.41.0,>=1.40.0
Requires-Dist: openai<2.0.0,>=1.11.0
Requires-Dist: requests<3.0.0,>=2.32.4
Requires-Dist: numpy<2.0.0,>=1.26.0
Requires-Dist: pandas<3.0.0,>=2.2.0
Requires-Dist: faker<25.0.0,>=24.0.0
Requires-Dist: python-dateutil<3.0.0,>=2.8.0
Requires-Dist: pytz<2025.0,>=2024.0
Requires-Dist: tqdm<5.0.0,>=4.66.3
Requires-Dist: tiktoken<1.0.0,>=0.5.0
Requires-Dist: google-cloud-aiplatform<2.0.0,>=1.38.0
Requires-Dist: google-auth<3.0.0,>=2.23.0
Requires-Dist: vertexai<2.0.0,>=1.43.0
Requires-Dist: google-generativeai<1.0.0,>=0.8.0
Provides-Extra: dev
Requires-Dist: pytest>=7.0.0; extra == "dev"
Requires-Dist: pytest-cov>=4.0.0; extra == "dev"
Requires-Dist: black>=23.0.0; extra == "dev"
Requires-Dist: flake8>=6.0.0; extra == "dev"
Requires-Dist: mypy>=1.0.0; extra == "dev"
Dynamic: license-file
